angr/__init__.py
angr/__main__.py
angr/ail_callable.py
angr/annocfg.py
angr/blade.py
angr/block.py
angr/callable.py
angr/calling_conventions.py
angr/code_location.py
angr/codenode.py
angr/emulator.py
angr/errors.py
angr/factory.py
angr/graph_utils.py
angr/keyed_region.py
angr/knowledge_base.py
angr/project.py
angr/py.typed
angr/rustylib.cpython-312-aarch64-linux-gnu.so
angr/serializable.py
angr/sim_manager.py
angr/sim_options.py
angr/sim_procedure.py
angr/sim_state.py
angr/sim_state_options.py
angr/sim_type.py
angr/sim_variable.py
angr/slicer.py
angr/state_hierarchy.py
angr/tablespecs.py
angr/unicornlib.so
angr/vaults.py
angr/ailment/__init__.py
angr/ailment/block.py
angr/ailment/block_walker.py
angr/ailment/constant.py
angr/ailment/converter_common.py
angr/ailment/converter_pcode.py
angr/ailment/converter_vex.py
angr/ailment/expression.py
angr/ailment/manager.py
angr/ailment/statement.py
angr/ailment/tagged_object.py
angr/ailment/utils.py
angr/analyses/__init__.py
angr/analyses/analysis.py
angr/analyses/backward_slice.py
angr/analyses/binary_optimizer.py
angr/analyses/bindiff.py
angr/analyses/boyscout.py
angr/analyses/callee_cleanup_finder.py
angr/analyses/cdg.py
angr/analyses/class_identifier.py
angr/analyses/code_tagging.py
angr/analyses/codecave.py
angr/analyses/complete_calling_conventions.py
angr/analyses/congruency_check.py
angr/analyses/datagraph_meta.py
angr/analyses/ddg.py
angr/analyses/disassembly.py
angr/analyses/disassembly_utils.py
angr/analyses/dominance_frontier.py
angr/analyses/find_objects_static.py
angr/analyses/init_finder.py
angr/analyses/loop_analysis.py
angr/analyses/loopfinder.py
angr/analyses/patchfinder.py
angr/analyses/pathfinder.py
angr/analyses/proximity_graph.py
angr/analyses/reassembler.py
angr/analyses/s_liveness.py
angr/analyses/s_propagator.py
angr/analyses/smc.py
angr/analyses/soot_class_hierarchy.py
angr/analyses/stack_pointer_tracker.py
angr-9.2.193.dist-info/METADATA
angr-9.2.193.dist-info/WHEEL
angr-9.2.193.dist-info/entry_points.txt
angr-9.2.193.dist-info/top_level.txt
angr-9.2.193.dist-info/RECORD
angr-9.2.193.dist-info/licenses/LICENSE
