Metadata-Version: 2.4
Name: angr
Version: 9.2.193
Summary: A multi-architecture binary analysis toolkit, with the ability to perform dynamic symbolic execution and various static analyses on binaries
License-Expression: BSD-2-Clause
Project-URL: Homepage, https://angr.io/
Project-URL: Repository, https://github.com/angr/angr
Classifier: Programming Language :: Python :: 3
Classifier: Programming Language :: Python :: 3 :: Only
Classifier: Programming Language :: Python :: 3.10
Classifier: Programming Language :: Python :: 3.11
Classifier: Programming Language :: Python :: 3.12
Classifier: Programming Language :: Python :: 3.13
Requires-Python: >=3.10
License-File: LICENSE
Requires-Dist: cxxheaderparser
Requires-Dist: GitPython
Requires-Dist: archinfo==9.2.193
Requires-Dist: cachetools
Requires-Dist: capstone==5.0.3
Requires-Dist: cffi>=1.14.0
Requires-Dist: claripy==9.2.193
Requires-Dist: cle==9.2.193
Requires-Dist: lmdb
Requires-Dist: msgspec
Requires-Dist: mulpyplexer
Requires-Dist: networkx!=2.8.1,>=2.0
Requires-Dist: protobuf>=6.33.0
Requires-Dist: psutil
Requires-Dist: pycparser>=2.18
Requires-Dist: pydemumble
Requires-Dist: pyformlang
Requires-Dist: pypcode<4.0,>=3.2.1
Requires-Dist: pyvex==9.2.193
Requires-Dist: rich>=13.1.0
Requires-Dist: sortedcontainers
Requires-Dist: sympy
Requires-Dist: typing-extensions
Requires-Dist: unique-log-filter
Requires-Dist: colorama; platform_system == "Windows"
Provides-Extra: angrdb
Requires-Dist: sqlalchemy; extra == "angrdb"
Provides-Extra: keystone
Requires-Dist: keystone-engine; extra == "keystone"
Provides-Extra: telemetry
Requires-Dist: opentelemetry-api; extra == "telemetry"
Provides-Extra: unicorn
Requires-Dist: unicorn==2.0.1.post1; extra == "unicorn"
Requires-Dist: setuptools; extra == "unicorn"
Dynamic: license-file
